django_template_tree-0.1.1.dist-info/DESCRIPTION.rst
django_template_tree-0.1.1.dist-info/METADATA
django_template_tree-0.1.1.dist-info/RECORD
django_template_tree-0.1.1.dist-info/WHEEL
django_template_tree-0.1.1.dist-info/metadata.json
django_template_tree-0.1.1.dist-info/top_level.txt
template_tree/__init__.py
template_tree/apps.py
template_tree/models.py
template_tree/template_finder.py
template_tree/template_reader.py
template_tree/urls.py
template_tree/views.py
