Metadata-Version: 2.0
Name: django-template-tree
Version: 0.1.1
Summary: Generate diagrams showing relationships between templates in Django projects
Home-page: https://github.com/paul-butcher/django_template_tree
Author: Paul Butcher
Author-email: paul.butcher@gmail.com
License: MIT
Keywords: django_template_tree
Platform: UNKNOWN
Classifier: Development Status :: 3 - Alpha
Classifier: Framework :: Django
Classifier: Framework :: Django :: 1.8
Classifier: Framework :: Django :: 1.9
Classifier: Framework :: Django :: 1.10
Classifier: Intended Audience :: Developers
Classifier: License :: OSI Approved :: BSD License
Classifier: Natural Language :: English
Classifier: Programming Language :: Python :: 2
Classifier: Programming Language :: Python :: 2.7
Classifier: Programming Language :: Python :: 3
Classifier: Programming Language :: Python :: 3.3
Classifier: Programming Language :: Python :: 3.4
Classifier: Programming Language :: Python :: 3.5
